{
  "MissingNo.": "Missingno",
  "Bulbasaur": "Bisasam",
  "Ivysaur": "Ivysaur",
  "Venusaur": "Venusaur",
  "Charmander": "Hitokage",
  "Charmeleon": "Rizādo",
  "Charizard": "Glurak",
  "Squirtle": "Schiggy",
  "Wartortle": "Kamēru",
  "Blastoise": "Kamex",
  "Caterpie": "Raupy",
  "Metapod": "Safcon",
  "Butterfree": "Smettbo",
  "Weedle": "Weedle",
  "Kakuna": "Kokūn",
  "Beedrill": "Supiā",
  "Pidgey": "Poppo",
  "Pidgeotto": "Pijon",
  "Pidgeot": "Pigeot",
  "Rattata": "Rattata",
  "Alolan Rattata": "Rattata",
  "Raticate": "Ratta",
  "Alolan Raticate": "Ratta",
  "Spearow": "Spearow",
  "Fearow": "Fearow",
  "Ekans": "Ābo",
  "Arbok": "Arbok",
  "Pikachu": "Pikachu",
  "Pikachu Rock Star": "Pikachu Rockeur",
  "Pikachu Belle": "Pikachu Lady",
  "Pikachu Pop Star": "Pikachu Star",
  "Pikachu Ph.D.": "Pikachu Ph.D.",
  "Pikachu Libre": "Pikachu Libre",
  "Original Cap Pikachu": "Original-Kappe",
  "Hoenn Cap Pikachu": "Hōenkyappu",
  "Sinnoh Cap Pikachu": "Shin'Ōkyappu",
  "Unova Cap Pikachu": "Isshukyappu",
  "Kalos Cap Pikachu": "Kalos-Kappe",
  "Alola Cap Pikachu": "Arōrakyappu",
  "Partner Cap Pikachu": "Partner-Kappe",
  "Partner Pikachu": "Pikachu",
  "Raichu": "Raichu",
  "Alolan Raichu": "Raichu",
  "Sandshrew": "Sand",
  "Alolan Sandshrew": "Sand",
  "Sandslash": "Sandpan",
  "Alolan Sandslash": "Sandpan",
  "Nidoran♀️": "Nidoran",
  "Nidorina": "Nidorina",
  "Nidoqueen": "Nidokuin",
  "Nidoran♂️": "Nidoran",
  "Nidorino": "Nidorino",
  "Nidoking": "Nidoking",
  "Clefairy": "Pippi",
  "Clefable": "Pixy",
  "Vulpix": "Rokon",
  "Alolan Vulpix": "Rokon",
  "Ninetales": "Kyūkon",
  "Alolan Ninetales": "Kyūkon",
  "Jigglypuff": "Purin",
  "Wigglytuff": "Pukurin",
  "Zubat": "Zubat",
  "Golbat": "Golbat",
  "Oddish": "Oddish",
  "Gloom": "Gloom",
  "Vileplume": "Giflor",
  "Paras": "Paras",
  "Parasect": "Parasek",
  "Venonat": "Konpan",
  "Venomoth": "Omot",
  "Diglett": "Digda",
  "Alolan Diglett": "Digda",
  "Dugtrio": "Digdri",
  "Alolan Dugtrio": "Digdri",
  "Meowth": "Nyāsu",
  "Alolan Meowth": "Nyāsu",
  "Galarian Meowth": "Nyāsu",
  "Persian": "Persian",
  "Alolan Persian": "Persian",
  "Psyduck": "Enton",
  "Golduck": "Golduck",
  "Mankey": "Mankī",
  "Primeape": "Rasaff",
  "Growlithe": "Gādi",
  "Hisuian Growlithe": "Gādi",
  "Arcanine": "Uindi",
  "Hisuian Arcanine": "Uindi",
  "Poliwag": "Poliwag",
  "Poliwhirl": "Nyorozo",
  "Poliwrath": "Quappo",
  "Abra": "Abra",
  "Kadabra": "Kadabra",
  "Alakazam": "Fūdin",
  "Machop": "Machop",
  "Machoke": "Gōrikī",
  "Machamp": "Machamp",
  "Bellsprout": "Knofensa",
  "Weepinbell": "Utsudon",
  "Victreebel": "Utsubot",
  "Tentacool": "Tentacha",
  "Tentacruel": "Tentoxa",
  "Geodude": "Geodude",
  "Alolan Geodude": "Geodude",
  "Graveler": "Gorōn",
  "Alolan Graveler": "Gorōn",
  "Golem": "Golem",
  "Alolan Golem": "Golem",
  "Ponyta": "Ponyta",
  "Galarian Ponyta": "Ponyta",
  "Rapidash": "Gallop",
  "Galarian Rapidash": "Gallop",
  "Slowpoke": "Yadon",
  "Galarian Slowpoke": "Yadon",
  "Slowbro": "Lahmus",
  "Galarian Slowbro": "Lahmus",
  "Magnemite": "Coil",
  "Magneton": "Magneton",
  "Farfetch'd": "Porenta",
  "Galarian Farfetch'd": "Porenta",
  "Doduo": "Dōdō",
  "Dodrio": "Dodri",
  "Seel": "Seel",
  "Dewgong": "Jugon",
  "Grimer": "Grimer",
  "Alolan Grimer": "Grimer",
  "Muk": "Muk",
  "Alolan Muk": "Muk",
  "Shellder": "Sherudā",
  "Cloyster": "Austos",
  "Gastly": "Gōsu",
  "Haunter": "Ghost",
  "Gengar": "Gengā",
  "Onix": "Onix",
  "Drowzee": "Surīpu",
  "Hypno": "Hypno",
  "Krabby": "Crab",
  "Kingler": "Kingler",
  "Voltorb": "Voltorb",
  "Hisuian Voltorb": "Voltorb",
  "Electrode": "Marumain",
  "Hisuian Electrode": "Marumain",
  "Exeggcute": "Owei",
  "Exeggutor": "Nassy",
  "Alolan Exeggutor": "Nassy",
  "Cubone": "Cubone",
  "Marowak": "Knogga",
  "Alolan Marowak": "Knogga",
  "Hitmonlee": "Kicklee",
  "Hitmonchan": "Tygnon",
  "Lickitung": "Schlurp",
  "Koffing": "Smogo",
  "Weezing": "Weezing",
  "Galarian Weezing": "Weezing",
  "Rhyhorn": "Saihōn",
  "Rhydon": "Sidon",
  "Chansey": "Rakkī",
  "Tangela": "Tangela",
  "Kangaskhan": "Garūra",
  "Horsea": "Tattu",
  "Seadra": "Seadra",
  "Goldeen": "Goldeen",
  "Seaking": "Azumaō",
  "Staryu": "Stari",
  "Starmie": "Sutāmī",
  "Mr. Mime": "M Mime",
  "Galarian Mr. Mime": "M Mime",
  "Scyther": "Strike",
  "Jynx": "Jynx",
  "Electabuzz": "Erebū",
  "Magmar": "Būbā",
  "Pinsir": "Pinsir",
  "Tauros": "Tauros",
  "Combat Breed Tauros": "Tauros",
  "Blaze Breed Tauros": "Tauros",
  "Aqua Breed Tauros": "Tauros",
  "Magikarp": "Koiking",
  "Gyarados": "Garados",
  "Lapras": "Lapras",
  "Ditto": "Ditto",
  "Eevee": "Ībui",
  "Partner Eevee": "Ībui",
  "Vaporeon": "Aquana",
  "Jolteon": "Blitza",
  "Flareon": "Būsutā",
  "Porygon": "Porygon",
  "Omanyte": "Omnite",
  "Omastar": "Omstar",
  "Kabuto": "Kabuto",
  "Kabutops": "Kabutops",
  "Aerodactyl": "Ptera",
  "Snorlax": "Relaxo",
  "Articuno": "Furīzā",
  "Galarian Articuno": "Furīzā",
  "Zapdos": "Sandā",
  "Galarian Zapdos": "Sandā",
  "Moltres": "Fire",
  "Galarian Moltres": "Fire",
  "Dratini": "Dratini",
  "Dragonair": "Draco",
  "Dragonite": "Kairyū",
  "Mewtwo": "Mewtu",
  "Mew": "Mew",
  "Chikorita": "Endivie",
  "Bayleef": "Bayleef",
  "Meganium": "Meganie",
  "Cyndaquil": "Feurigel",
  "Quilava": "Quilava",
  "Typhlosion": "Bakufūn",
  "Hisuian Typhlosion": "Bakufūn",
  "Totodile": "Totodile",
  "Croconaw": "Croconaw",
  "Feraligatr": "Ōdairu",
  "Sentret": "Otachi",
  "Furret": "Furret",
  "Hoothoot": "Hōhō",
  "Noctowl": "Noctuh",
  "Ledyba": "Coxy",
  "Ledian": "Ledian",
  "Spinarak": "Itomaru",
  "Ariados": "Ariados",
  "Crobat": "Crobat",
  "Chinchou": "Lampi",
  "Lanturn": "Rantān",
  "Pichu": "Pichu",
  "Spiky-eared Pichu": "Pichu",
  "Cleffa": "Pī",
  "Igglybuff": "Pupurin",
  "Togepi": "Togepi",
  "Togetic": "Togetic",
  "Natu": "Natu",
  "Xatu": "Xatu",
  "Mareep": "Mareep",
  "Flaaffy": "Waaty",
  "Ampharos": "Denryū",
  "Bellossom": "Blubella",
  "Marill": "Maril",
  "Azumarill": "Marilli",
  "Sudowoodo": "Usokkī",
  "Politoed": "Quaxo",
  "Hoppip": "Hoppip",
  "Skiploom": "Popokko",
  "Jumpluff": "Watakko",
  "Aipom": "Aipom",
  "Sunkern": "Sunkern",
  "Sunflora": "Sunflora",
  "Yanma": "Yanma",
  "Wooper": "Upā",
  "Paldean Wooper": "Upā",
  "Quagsire": "Nuō",
  "Espeon": "Ēfi",
  "Umbreon": "Blacky",
  "Murkrow": "Murkrow",
  "Slowking": "Roigada",
  "Galarian Slowking": "Roigada",
  "Misdreavus": "Mūma",
  "Unown": "Unown",
  "Unown A": "Unown",
  "Unown B": "Unown",
  "Unown C": "Unown",
  "Unown D": "Unown",
  "Unown E": "Unown",
  "Unown G": "Unown",
  "Unown H": "Unown",
  "Unown I": "Unown",
  "Unown J": "Unown",
  "Unown K": "Unown",
  "Unown L": "Unown",
  "Unown M": "Unown",
  "Unown N": "Unown",
  "Unown O": "Unown",
  "Unown P": "Unown",
  "Unown Q": "Unown",
  "Unown R": "Unown",
  "Unown S": "Unown",
  "Unown T": "Unown",
  "Unown U": "Unown",
  "Unown V": "Unown",
  "Unown W": "Unown",
  "Unown X": "Unown",
  "Unown Y": "Unown",
  "Unown Z": "Unown",
  "Unown Exclamation": "Unown",
  "Unown Question": "Unown",
  "Wobbuffet": "Sonans",
  "Girafarig": "Girafarig",
  "Pineco": "Pineco",
  "Forretress": "Foretos",
  "Dunsparce": "Nokotchi",
  "Gligar": "Gligar",
  "Steelix": "Steelix",
  "Snubbull": "Burū",
  "Granbull": "Granbull",
  "Qwilfish": "Harīsen",
  "Hisuian Qwilfish": "Harīsen",
  "Scizor": "Scizor",
  "Shuckle": "Shuckle",
  "Heracross": "Heracros",
  "Sneasel": "Nyūra",
  "Hisuian Sneasel": "Nyūra",
  "Teddiursa": "Himeguma",
  "Ursaring": "Ringuma",
  "Slugma": "Slugma",
  "Magcargo": "Magcargo",
  "Swinub": "Urimū",
  "Piloswine": "Inomū",
  "Corsola": "Sanīgo",
  "Galarian Corsola": "Sanīgo",
  "Remoraid": "Teppōō",
  "Octillery": "Okutan",
  "Delibird": "Botogel",
  "Mantine": "Mantax",
  "Skarmory": "Airmd",
  "Houndour": "Delvil",
  "Houndoom": "Herugā",
  "Kingdra": "Kingdra",
  "Phanpy": "Phanpy",
  "Donphan": "Donfan",
  "Porygon2": "Porygon2",
  "Stantler": "Stantler",
  "Smeargle": "Doble",
  "Tyrogue": "Barukī",
  "Hitmontop": "Kapoerā",
  "Smoochum": "Muchul",
  "Elekid": "Elekid",
  "Magby": "Bubī",
  "Miltank": "Miltank",
  "Blissey": "Blissey",
  "Raikou": "Raikō",
  "Entei": "Entei",
  "Suicune": "Suikun",
  "Larvitar": "Yogiras",
  "Pupitar": "Pupitar",
  "Tyranitar": "Bangiras",
  "Lugia": "Lugia",
  "Ho-Oh": "Hōō",
  "Celebi": "Celebi",
  "Treecko": "Arcko",
  "Grovyle": "Massko",
  "Sceptile": "Jukain",
  "Torchic": "Achamo",
  "Combusken": "Galifeu",
  "Blaziken": "Bashāmo",
  "Mudkip": "Gobou",
  "Marshtomp": "Flobio",
  "Swampert": "Sumpex",
  "Poochyena": "Fiffyen",
  "Mightyena": "Graena",
  "Zigzagoon": "Zigzachs",
  "Galarian Zigzagoon": "Zigzachs",
  "Linoone": "Linéon",
  "Galarian Linoone": "Linéon",
  "Wurmple": "Wurmple",
  "Silcoon": "Silcoon",
  "Beautifly": "Agehunt",
  "Cascoon": "Mayuld",
  "Dustox": "Pudox",
  "Lotad": "Lotad",
  "Lombre": "Lombre",
  "Ludicolo": "Ludicolo",
  "Seedot": "Seedot",
  "Nuzleaf": "Blanas",
  "Shiftry": "Shiftry",
  "Taillow": "Subame",
  "Swellow": "Swellow",
  "Wingull": "Camome",
  "Pelipper": "Perippā",
  "Ralts": "Ralts",
  "Kirlia": "Kirlia",
  "Gardevoir": "Sānaito",
  "Surskit": "Arakdo",
  "Masquerain": "Amemōsu",
  "Shroomish": "Knilz",
  "Breloom": "Kapilz",
  "Slakoth": "Slakoth",
  "Vigoroth": "Muntier",
  "Slaking": "Slaking",
  "Nincada": "Nincada",
  "Ninjask": "Ninjask",
  "Shedinja": "Munja",
  "Whismur": "Whismur",
  "Loudred": "Dogōmu",
  "Exploud": "Exploud",
  "Makuhita": "Makuhita",
  "Hariyama": "Hariyama",
  "Azurill": "Ruriri",
  "Nosepass": "Nasgnet",
  "Skitty": "Eneko",
  "Delcatty": "Enekoro",
  "Sableye": "Sableye",
  "Mawile": "Mawile",
  "Aron": "Aron",
  "Lairon": "Lairon",
  "Aggron": "Aggron",
  "Meditite": "Asanan",
  "Medicham": "Charem",
  "Electrike": "Rakurai",
  "Manectric": "Livolt",
  "Plusle": "Plusle",
  "Minun": "Minun",
  "Volbeat": "Volbeat",
  "Illumise": "Irumīze",
  "Roselia": "Roselia",
  "Gulpin": "Gulpin",
  "Swalot": "Swalot",
  "Carvanha": "Kibania",
  "Sharpedo": "Tohaido",
  "Wailmer": "Wailmer",
  "Wailord": "Hoeruō",
  "Numel": "Numel",
  "Camerupt": "Bakūda",
  "Torkoal": "Kōtasu",
  "Spoink": "Spoink",
  "Grumpig": "Boopig",
  "Spinda": "Spinda",
  "Trapinch": "Nakkurā",
  "Vibrava": "Vibrava",
  "Flygon": "Flygon",
  "Cacnea": "Tuska",
  "Cacturne": "Noctus",
  "Swablu": "Wablu",
  "Altaria": "Altaria",
  "Zangoose": "Sengo",
  "Seviper": "Seviper",
  "Lunatone": "Runatōn",
  "Solrock": "Solrock",
  "Barboach": "Dojoach",
  "Whiscash": "Welsar",
  "Corphish": "Heigani",
  "Crawdaunt": "Crawdaunt",
  "Baltoy": "Baltoy",
  "Claydol": "Claydol",
  "Lileep": "Lilia",
  "Cradily": "Wielie",
  "Anorith": "Anopth",
  "Armaldo": "Armaldo",
  "Feebas": "Feebas",
  "Milotic": "Milotic",
  "Castform": "Formeo",
  "Sunny Castform": "Formeo",
  "Rainy Castform": "Formeo",
  "Snowy Castform": "Formeo",
  "Kecleon": "Kecleon",
  "Shuppet": "Shuppet",
  "Banette": "Banette",
  "Duskull": "Duskull",
  "Dusclops": "Dusclops",
  "Tropius": "Tropius",
  "Chimecho": "Éoko",
  "Absol": "Absol",
  "Wynaut": "Isso",
  "Snorunt": "Snorunt",
  "Glalie": "Glalie",
  "Spheal": "Spheal",
  "Sealeo": "Sealeo",
  "Walrein": "Walrein",
  "Clamperl": "Perlu",
  "Huntail": "Huntail",
  "Gorebyss": "Gorebyss",
  "Relicanth": "Glanth",
  "Luvdisc": "Luvdisc",
  "Bagon": "Bagon",
  "Shelgon": "Komorū",
  "Salamence": "Bōmanda",
  "Beldum": "Beldum",
  "Metang": "Metang",
  "Metagross": "Metagross",
  "Regirock": "Regirock",
  "Regice": "Regice",
  "Registeel": "Registeel",
  "Latias": "Latias",
  "Latios": "Latios",
  "Kyogre": "Kyogre",
  "Groudon": "Groudon",
  "Rayquaza": "Rekkūza",
  "Jirachi": "Jirachi",
  "Deoxys": "Deoxys",
  "Speed Deoxys": "Deoxys",
  "Attack Deoxys": "Deoxys",
  "Defense Deoxys": "Deoxys",
  "Turtwig": "Naetle",
  "Grotle": "Grotle",
  "Torterra": "Torterra",
  "Chimchar": "Panflam",
  "Monferno": "Panpyro",
  "Infernape": "Gōkazaru",
  "Piplup": "Piplup",
  "Prinplup": "Pliprin",
  "Empoleon": "Emperte",
  "Starly": "Starly",
  "Staravia": "Staravia",
  "Staraptor": "Mukuhōku",
  "Bidoof": "Bippa",
  "Bibarel": "Bīdaru",
  "Kricketot": "Crikzik",
  "Kricketune": "Korotock",
  "Shinx": "Lixy",
  "Luxio": "Luxio",
  "Luxray": "Luxray",
  "Budew": "Budew",
  "Roserade": "Roserade",
  "Cranidos": "Cranidos",
  "Rampardos": "Rampald",
  "Shieldon": "Shieldon",
  "Bastiodon": "Torideps",
  "Burmy": "Burmy",
  "Sandy Burmy": "Burmy",
  "Trash Burmy": "Burmy",
  "Wormadam": "Wormadam",
  "Sandy Wormadam": "Wormadam",
  "Trash Wormadam": "Wormadam",
  "Mothim": "Mothim",
  "Combee": "Combee",
  "Vespiquen": "Bīkuin",
  "Pachirisu": "Pachirisu",
  "Buizel": "Buizel",
  "Floatzel": "Floazel",
  "Cherubi": "Kikugi",
  "Cherrim": "Kinoso",
  "Sunshine Cherrim": "Kinoso",
  "Shellos": "Shellos",
  "East Sea Shellos": "Shellos",
  "Gastrodon": "Tritodon",
  "East Sea Gastrodon": "Tritodon",
  "Ambipom": "Ambipom",
  "Drifloon": "Fuwante",
  "Drifblim": "Drifblim",
  "Buneary": "Buneary",
  "Lopunny": "Lopunny",
  "Mismagius": "Mūmāji",
  "Honchkrow": "Corboss",
  "Glameow": "Glameow",
  "Purugly": "Purugly",
  "Chingling": "Rīshan",
  "Stunky": "Stunky",
  "Skuntank": "Skutank",
  "Bronzor": "Dōmirā",
  "Bronzong": "Dōtakun",
  "Bonsly": "Mobai",
  "Mime Jr.": "Manene",
  "Happiny": "Happiny",
  "Chatot": "Perap",
  "Spiritomb": "Kryppuk",
  "Gible": "Gible",
  "Gabite": "Gabite",
  "Garchomp": "Garchomp",
  "Munchlax": "Gonbe",
  "Riolu": "Riolu",
  "Lucario": "Lucario",
  "Hippopotas": "Hippopotas",
  "Hippowdon": "Kabaldon",
  "Skorupi": "Rapion",
  "Drapion": "Drapion",
  "Croagunk": "Croagunk",
  "Toxicroak": "Coatox",
  "Carnivine": "Muskippa",
  "Finneon": "Keikōō",
  "Lumineon": "Neolant",
  "Mantyke": "Mantyke",
  "Snover": "Snover",
  "Abomasnow": "Yukinōō",
  "Weavile": "Weavile",
  "Magnezone": "Jibacoil",
  "Lickilicky": "Berobelt",
  "Rhyperior": "Dosidon",
  "Tangrowth": "Mojanbo",
  "Electivire": "Elekible",
  "Magmortar": "Būbān",
  "Togekiss": "Togekiss",
  "Yanmega": "Yanmega",
  "Leafeon": "Rīfia",
  "Glaceon": "Glacia",
  "Gliscor": "Glion",
  "Mamoswine": "Manmū",
  "Porygon-Z": "Porigonz",
  "Gallade": "Gallade",
  "Probopass": "Dainōzu",
  "Dusknoir": "Yonoir",
  "Froslass": "Froslass",
  "Rotom": "Rotom",
  "Heat Rotom": "Rotom",
  "Wash Rotom": "Rotom",
  "Frost Rotom": "Rotom",
  "Fan Rotom": "Rotom",
  "Mow Rotom": "Rotom",
  "Rotom Pokédex": "Rotom",
  "Rotom Phone": "Rotom",
  "Rotom Drone": "Rotom",
  "Uxie": "Uxie",
  "Mesprit": "Emrit",
  "Azelf": "Azelf",
  "Dialga": "Dialga",
  "Palkia": "Palkia",
  "Heatran": "Heatran",
  "Regigigas": "Regigigas",
  "Giratina": "Giratina",
  "Cresselia": "Cresselia",
  "Phione": "Fione",
  "Manaphy": "Manafi",
  "Darkrai": "Darkrai",
  "Shaymin": "Sheimi",
  "Arceus": "Arceus",
  "Bug Arceus": "Arceus",
  "Dark Arceus": "Arceus",
  "Dragon Arceus": "Arceus",
  "Electric Arceus": "Arceus",
  "Fighting Arceus": "Arceus",
  "Fire Arceus": "Arceus",
  "Flying Arceus": "Arceus",
  "Ghost Arceus": "Arceus",
  "Grass Arceus": "Arceus",
  "Ground Arceus": "Arceus",
  "Ice Arceus": "Arceus",
  "Poison Arceus": "Arceus",
  "Psychic Arceus": "Arceus",
  "Rock Arceus": "Arceus",
  "Steel Arceus": "Arceus",
  "Water Arceus": "Arceus",
  "Fairy Arceus": "Arceus",
  "Victini": "Victini",
  "Snivy": "Snivy",
  "Servine": "Janobī",
  "Serperior": "Jarōda",
  "Tepig": "Tepig",
  "Pignite": "Chaobū",
  "Emboar": "Enbuō",
  "Oshawott": "Ottaro",
  "Dewott": "Dewott",
  "Samurott": "Admurai",
  "Hisuian Samurott": "Admurai",
  "Patrat": "Patrat",
  "Watchog": "Watchog",
  "Lillipup": "Yōterī",
  "Herdier": "Herdier",
  "Stoutland": "Mūrando",
  "Purrloin": "Felilou",
  "Liepard": "Liepard",
  "Pansage": "Pansage",
  "Simisage": "Yanakkī",
  "Pansear": "Baoppu",
  "Simisear": "Baokkī",
  "Panpour": "Panpour",
  "Simipour": "Hiyakkī",
  "Munna": "Munna",
  "Musharna": "Mushāna",
  "Pidove": "Pidove",
  "Tranquill": "Hatōbō",
  "Unfezant": "Kenhorō",
  "Blitzle": "Blitzle",
  "Zebstrika": "Zebritz",
  "Roggenrola": "Dangoro",
  "Boldore": "Gantle",
  "Gigalith": "Gigalith",
  "Woobat": "Woobat",
  "Swoobat": "Swoobat",
  "Drilbur": "Drilbur",
  "Excadrill": "Doryūzu",
  "Audino": "Audino",
  "Timburr": "Timburr",
  "Gurdurr": "Gurdurr",
  "Conkeldurr": "Rōbushin",
  "Tympole": "Tympole",
  "Palpitoad": "Mebrana",
  "Seismitoad": "Branawarz",
  "Throh": "Throh",
  "Sawk": "Sawk",
  "Sewaddle": "Sewaddle",
  "Swadloon": "Folikon",
  "Leavanny": "Leavanny",
  "Venipede": "Fushide",
  "Whirlipede": "Hoīga",
  "Scolipede": "Pendorā",
  "Cottonee": "Monmen",
  "Whimsicott": "Elfun",
  "Petilil": "Petilil",
  "Lilligant": "Doredia",
  "Hisuian Lilligant": "Doredia",
  "Basculin": "Basurao",
  "Blue-Striped Basculin": "Basurao",
  "White-Striped Basculin": "Basurao",
  "Sandile": "Sandile",
  "Krokorok": "Escroco",
  "Krookodile": "Waruvial",
  "Darumaka": "Darumaka",
  "Galarian Darumaka": "Darumaka",
  "Darmanitan": "Darumacho",
  "Zen Darmanitan": "Darumacho",
  "Galarian Darmanitan": "Darumacho",
  "Galarian Zen Darmanitan": "Darumacho",
  "Maractus": "Maractus",
  "Dwebble": "Dwebble",
  "Crustle": "Crustle",
  "Scraggy": "Scraggy",
  "Scrafty": "Irokex",
  "Sigilyph": "Sigilyph",
  "Yamask": "Yamask",
  "Galarian Yamask": "Yamask",
  "Cofagrigus": "Desukān",
  "Tirtouga": "Protoga",
  "Carracosta": "Abagōra",
  "Archen": "Āken",
  "Archeops": "Ākeosu",
  "Trubbish": "Trubbish",
  "Garbodor": "Dustdas",
  "Zorua": "Zorua",
  "Hisuian Zorua": "Zorua",
  "Zoroark": "Zoroark",
  "Hisuian Zoroark": "Zoroark",
  "Minccino": "Chirāmī",
  "Cinccino": "Cinccino",
  "Gothita": "Gothita",
  "Gothorita": "Gothorita",
  "Gothitelle": "Sidérella",
  "Solosis": "Uniran",
  "Duosion": "Méios",
  "Reuniclus": "Symbios",
  "Ducklett": "Koaruhī",
  "Swanna": "Swanna",
  "Vanillite": "Sorbébé",
  "Vanillish": "Sorboul",
  "Vanilluxe": "Vanilluxe",
  "Deerling": "Deerling",
  "Summer Deerling": "Deerling",
  "Autumn Deerling": "Deerling",
  "Winter Deerling": "Deerling",
  "Sawsbuck": "Haydaim",
  "Summer Sawsbuck": "Haydaim",
  "Autumn Sawsbuck": "Haydaim",
  "Winter Sawsbuck": "Haydaim",
  "Emolga": "Emolga",
  "Karrablast": "Laukaps",
  "Escavalier": "Chevargo",
  "Foongus": "Foongus",
  "Amoonguss": "Gaulet",
  "Frillish": "Quabbel",
  "Jellicent": "Moyade",
  "Alomomola": "Mamanbō",
  "Joltik": "Joltik",
  "Galvantula": "Dentula",
  "Ferroseed": "Tesseed",
  "Ferrothorn": "Nutrey",
  "Klink": "Tic",
  "Klang": "Clic",
  "Klinklang": "Klinklang",
  "Tynamo": "Tynamo",
  "Eelektrik": "Eelektrik",
  "Eelektross": "Eelektross",
  "Elgyem": "Elgyem",
  "Beheeyem": "Ōbemu",
  "Litwick": "Litwick",
  "Lampent": "Lampent",
  "Chandelure": "Shandera",
  "Axew": "Axew",
  "Fraxure": "Onondo",
  "Haxorus": "Maxax",
  "Cubchoo": "Cubchoo",
  "Beartic": "Beartic",
  "Cryogonal": "Furījio",
  "Shelmet": "Shelmet",
  "Accelgor": "Agirudā",
  "Stunfisk": "Maggyo",
  "Galarian Stunfisk": "Maggyo",
  "Mienfoo": "Kojofū",
  "Mienshao": "Kojondo",
  "Druddigon": "Crimgan",
  "Golett": "Gobit",
  "Golurk": "Golurk",
  "Pawniard": "Pawniard",
  "Bisharp": "Bisharp",
  "Bouffalant": "Frison",
  "Rufflet": "Rufflet",
  "Braviary": "Wōguru",
  "Hisuian Braviary": "Wōguru",
  "Vullaby": "Vullaby",
  "Mandibuzz": "Vulgina",
  "Heatmor": "Heatmor",
  "Durant": "Aiant",
  "Deino": "Deino",
  "Zweilous": "Dihead",
  "Hydreigon": "Hydreigon",
  "Larvesta": "Ignivor",
  "Volcarona": "Pyrax",
  "Cobalion": "Cobalon",
  "Terrakion": "Terakion",
  "Virizion": "Virizion",
  "Tornadus": "Boreos",
  "Thundurus": "Voltolos",
  "Reshiram": "Reshiram",
  "Zekrom": "Zekrom",
  "Landorus": "Landlos",
  "Kyurem": "Kyurem",
  "Keldeo": "Keldeo",
  "Meloetta": "Meloetta",
  "Pirouette Meloetta": "Tanzform",
  "Genesect": "Genesect",
  "High-speed Flight Configuration Genesect": "Genesect",
  "Chespin": "Chespin",
  "Quilladin": "Haribōgu",
  "Chesnaught": "Brigaron",
  "Fennekin": "Fynx",
  "Braixen": "Tērunā",
  "Delphox": "Mahoxy",
  "Froakie": "Froxy",
  "Frogadier": "Amphizel",
  "Greninja": "Gekkōga",
  "Ash's Greninja": "Ash-Form",
  "Bunnelby": "Horubī",
  "Diggersby": "Horūdo",
  "Fletchling": "Dartiri",
  "Fletchinder": "Dartignis",
  "Talonflame": "Fiaro",
  "Scatterbug": "Purmel",
  "Spewpa": "Spewpa",
  "Vivillon": "Bibiyon",
  "Icy Snow Vivillon": "Bibiyon",
  "Polar Vivillon": "Bibiyon",
  "Tundra Vivillon": "Bibiyon",
  "Continental Vivillon": "Bibiyon",
  "Garden Vivillon": "Bibiyon",
  "Elegant Vivillon": "Bibiyon",
  "Modern Vivillon": "Bibiyon",
  "Marine Vivillon": "Bibiyon",
  "Archipelago Vivillon": "Bibiyon",
  "High Plain Vivillon": "Bibiyon",
  "Sandstorm Vivillon": "Bibiyon",
  "River Vivillon": "Bibiyon",
  "Monsoon Vivillon": "Bibiyon",
  "Savanna Vivillon": "Bibiyon",
  "Sun Vivillon": "Bibiyon",
  "Ocean Vivillon": "Bibiyon",
  "Jungle Vivillon": "Bibiyon",
  "Fancy Vivillon": "Bibiyon",
  "Poké Ball Vivillon": "Bibiyon",
  "Litleo": "Litleo",
  "Pyroar": "Pyroar",
  "Flabébé": "Flabébé",
  "Yellow Flower Flabébé": "Flabébé",
  "Orange Flower Flabébé": "Flabébé",
  "Blue Flower Flabébé": "Flabébé",
  "White Flower Flabébé": "Flabébé",
  "Floette": "Floette",
  "Yellow Flower Floette": "Floette",
  "Orange Flower Floette": "Floette",
  "Blue Flower Floette": "Floette",
  "White Flower Floette": "Floette",
  "Florges": "Florges",
  "Yellow Flower Florges": "Florges",
  "Orange Flower Florges": "Florges",
  "Blue Flower Florges": "Florges",
  "White Flower Florges": "Florges",
  "Skiddo": "Skiddo",
  "Gogoat": "Gogoat",
  "Pancham": "Pancham",
  "Pangoro": "Pangoro",
  "Furfrou": "Furfrou",
  "Heart Trim Furfrou": "Furfrou",
  "Star Trim Furfrou": "Furfrou",
  "Diamond Trim Furfrou": "Furfrou",
  "Debutante Trim Furfrou": "Furfrou",
  "Matron Trim Furfrou": "Furfrou",
  "Dandy Trim Furfrou": "Furfrou",
  "La Reine Trim Furfrou": "Furfrou",
  "Kabuki Trim Furfrou": "Furfrou",
  "Pharaoh Trim Furfrou": "Furfrou",
  "Espurr": "Psiau",
  "Meowstic": "Nyaonix",
  "Honedge": "Honedge",
  "Doublade": "Duokles",
  "Aegislash": "Exagide",
  "Blade Aegislash": "Exagide",
  "Spritzee": "Parfi",
  "Aromatisse": "Frefuwan",
  "Swirlix": "Swirlix",
  "Slurpuff": "Slurpuff",
  "Inkay": "Inkay",
  "Malamar": "Malamar",
  "Binacle": "Binacle",
  "Barbaracle": "Gamenodes",
  "Skrelp": "Skrelp",
  "Dragalge": "Tandrak",
  "Clauncher": "Udeppō",
  "Clawitzer": "Wummer",
  "Helioptile": "Eguana",
  "Heliolisk": "Erezādo",
  "Tyrunt": "Tyrunt",
  "Tyrantrum": "Tyrantrum",
  "Amaura": "Amaura",
  "Aurorus": "Aurorus",
  "Sylveon": "Ninfia",
  "Hawlucha": "Hawlucha",
  "Dedenne": "Dedenne",
  "Carbink": "Rocara",
  "Goomy": "Goomy",
  "Sliggoo": "Numeil",
  "Hisuian Sliggoo": "Numeil",
  "Goodra": "Goodra",
  "Hisuian Goodra": "Goodra",
  "Klefki": "Klefki",
  "Phantump": "Bokurē",
  "Trevenant": "Ohrot",
  "Pumpkaboo": "Irrbis",
  "Small Pumpkaboo": "Größe S",
  "Large Pumpkaboo": "Größe L",
  "Super Pumpkaboo": "Größe XL",
  "Gourgeist": "Pumpjin",
  "Small Gourgeist": "Größe S",
  "Large Gourgeist": "Größe L",
  "Super Gourgeist": "Größe XL",
  "Bergmite": "Arktip",
  "Avalugg": "Avalugg",
  "Hisuian Avalugg": "Avalugg",
  "Noibat": "Onbat",
  "Noivern": "Onbān",
  "Xerneas": "Xerneas",
  "Neutral Xerneas": "Xerneas",
  "Yveltal": "Yveltal",
  "Zygarde": "Zygarde",
  "10% Zygarde": "Zygarde",
  "Complete Zygarde": "Zygarde",
  "Zygarde Cell": "Zygarde",
  "Zygarde Core": "Zygarde",
  "Diancie": "Diancie",
  "Hoopa": "Fūpa",
  "Volcanion": "Volcanion",
  "Rowlet": "Bauz",
  "Dartrix": "Dartrix",
  "Decidueye": "Junaipā",
  "Hisuian Decidueye": "Junaipā",
  "Litten": "Nyabī",
  "Torracat": "Nyahīto",
  "Incineroar": "Fuegro",
  "Popplio": "Popplio",
  "Brionne": "Brionne",
  "Primarina": "Ashirēnu",
  "Pikipek": "Pikipek",
  "Trumbeak": "Trumbeak",
  "Toucannon": "Tukanon",
  "Yungoos": "Yungoos",
  "Gumshoos": "Gumshoos",
  "Grubbin": "Mabula",
  "Charjabug": "Akkup",
  "Vikavolt": "Lucanon",
  "Crabrawler": "Krabbox",
  "Crabominable": "Krawell",
  "Oricorio": "Oricorio",
  "Pom-pom Oricorio": "Oricorio",
  "Pa'u Oricorio": "Oricorio",
  "Sensu Oricorio": "Oricorio",
  "Cutiefly": "Aburī",
  "Ribombee": "Ribombee",
  "Rockruff": "Iwanko",
  "Lycanroc": "Lycanroc",
  "Midnight Lycanroc": "Lycanroc",
  "Dusk Lycanroc": "Lycanroc",
  "Wishiwashi": "Yowashi",
  "School Wishiwashi": "Yowashi",
  "Mareanie": "Hidoide",
  "Toxapex": "Toxapex",
  "Mudbray": "Mudbray",
  "Mudsdale": "Mudsdale",
  "Dewpider": "Araqua",
  "Araquanid": "Araquanid",
  "Fomantis": "Imantis",
  "Lurantis": "Lurantis",
  "Morelull": "Nemashu",
  "Shiinotic": "Mashēdo",
  "Salandit": "Molunk",
  "Salazzle": "Ennewt",
  "Stufful": "Stufful",
  "Bewear": "Bewear",
  "Bounsweet": "Amakaji",
  "Steenee": "Steenee",
  "Tsareena": "Amājo",
  "Comfey": "Comfey",
  "Oranguru": "Oranguru",
  "Passimian": "Passimian",
  "Wimpod": "Wimpod",
  "Golisopod": "Tectass",
  "Sandygast": "Sunabā",
  "Palossand": "Palossand",
  "Pyukumuku": "Gufa",
  "Type: Null": "Type0",
  "Silvally": "Silvady",
  "Bug Silvally": "Silvady",
  "Dark Silvally": "Silvady",
  "Dragon Silvally": "Silvady",
  "Electric Silvally": "Silvady",
  "Fighting Silvally": "Silvady",
  "Fire Silvally": "Silvady",
  "Flying Silvally": "Silvady",
  "Ghost Silvally": "Silvady",
  "Grass Silvally": "Silvady",
  "Ground Silvally": "Silvady",
  "Ice Silvally": "Silvady",
  "Poison Silvally": "Silvady",
  "Psychic Silvally": "Silvady",
  "Rock Silvally": "Silvady",
  "Steel Silvally": "Silvady",
  "Water Silvally": "Silvady",
  "Fairy Silvally": "Silvady",
  "Minior": "Minior",
  "Komala": "Komala",
  "Turtonator": "Boumata",
  "Togedemaru": "Togedemaru",
  "Mimikyu": "Mimikyu",
  "Busted Mimikyu": "Mimikyu",
  "Bruxish": "Bruxish",
  "Drampa": "Drampa",
  "Dhelmise": "Moruda",
  "Jangmo-o": "Jarako",
  "Hakamo-o": "Écaïd",
  "Kommo-o": "Kommo-o",
  "Tapu Koko": "Tokorico",
  "Tapu Lele": "Tapu Lele",
  "Tapu Bulu": "Tokotoro",
  "Tapu Fini": "Tapu Fini",
  "Cosmog": "Cosmog",
  "Cosmoem": "Cosmoem",
  "Solgaleo": "Solgaleo",
  "Lunala": "Lunala",
  "Nihilego": "Anego",
  "Buzzwole": "Buzzwole",
  "Pheromosa": "Ferōche",
  "Xurkitree": "Xurkitree",
  "Celesteela": "Kaguron",
  "Kartana": "Kartana",
  "Guzzlord": "Guzzlord",
  "Necrozma": "Necrozma",
  "Magearna": "Magiana",
  "Marshadow": "Māshadō",
  "Zenith Marshadow": "Māshadō",
  "Poipole": "Vémini",
  "Naganadel": "Āgoyon",
  "Stakataka": "Ama-Ama",
  "Blacephalon": "Zugadōn",
  "Zeraora": "Zeraora",
  "Meltan": "Meltan",
  "Melmetal": "Melmetal",
  "Grookey": "Grookey",
  "Thwackey": "Thwackey",
  "Rillaboom": "Gortrom",
  "Scorbunny": "Hibanī",
  "Raboot": "Raboot",
  "Cinderace": "Ēsubān",
  "Sobble": "Sobble",
  "Drizzile": "Drizzile",
  "Inteleon": "Inteleon",
  "Skwovet": "Raffel",
  "Greedent": "Greedent",
  "Rookidee": "Meikro",
  "Corvisquire": "Aogarasu",
  "Corviknight": "Āmāgā",
  "Blipbug": "Blipbug",
  "Dottler": "Dottler",
  "Orbeetle": "Iorubu",
  "Nickit": "Nickit",
  "Thievul": "Gaunux",
  "Gossifleur": "Himenka",
  "Eldegoss": "Cottomi",
  "Wooloo": "Ūrū",
  "Dubwool": "Baiūrū",
  "Chewtle": "Chewtle",
  "Drednaw": "Kamalm",
  "Yamper": "Voldi",
  "Boltund": "Boltund",
  "Rolycoly": "Tandon",
  "Carkol": "Carkol",
  "Coalossal": "Coalossal",
  "Applin": "Applin",
  "Flapple": "Flapple",
  "Appletun": "Appletun",
  "Silicobra": "Dunaja",
  "Sandaconda": "Sadaija",
  "Cramorant": "Uu",
  "Gulping Cramorant": "Uu",
  "Gorging Cramorant": "Uu",
  "Arrokuda": "Pikuda",
  "Barraskewda": "Kamasujō",
  "Toxel": "Toxel",
  "Amped Toxtricity": "Riffex",
  "Low Key Toxtricity": "Riffex",
  "Sizzlipede": "Yakude",
  "Centiskorch": "Maruyakude",
  "Clobbopus": "Tatakko",
  "Grapploct": "Kaocto",
  "Sinistea": "Yabacha",
  "Polteageist": "Mortipot",
  "Hatenna": "Hatenna",
  "Hattrem": "Hattrem",
  "Hatterene": "Burimuon",
  "Impidimp": "Berobā",
  "Morgrem": "Gimō",
  "Grimmsnarl": "Ōronge",
  "Obstagoon": "Ixon",
  "Perrserker": "Nyaikingu",
  "Cursola": "Cursola",
  "Sirfetch'd": "Sirfetchd",
  "Mr. Rime": "Mr Rime",
  "Runerigus": "Desubān",
  "Milcery": "Crèmy",
  "Alcremie": "Pokusan",
  "Vanilla Cream Berry Sweet Alcremie": "Pokusan",
  "Vanilla Cream Love Sweet Alcremie": "Pokusan",
  "Vanilla Cream Star Sweet Alcremie": "Pokusan",
  "Vanilla Cream Clover Sweet Alcremie": "Pokusan",
  "Vanilla Cream Flower Sweet Alcremie": "Pokusan",
  "Vanilla Cream Ribbon Sweet Alcremie": "Pokusan",
  "Falinks": "Legios",
  "Pincurchin": "Wattapik",
  "Snom": "Snom",
  "Frosmoth": "Mosunō",
  "Stonjourner": "Dolman",
  "Eiscue": "Eiscue",
  "Noice Face Eiscue": "Eiscue",
  "Indeedee": "Iessan",
  "Morpeko": "Morpeko",
  "Hangry Morpeko": "Morpeko",
  "Cufant": "Zōdō",
  "Copperajah": "Daiōdō",
  "Dracozolt": "Galvagon",
  "Arctozolt": "Galvagla",
  "Dracovish": "Hydragon",
  "Arctovish": "Hydragla",
  "Duraludon": "Duraludon",
  "Dreepy": "Dreepy",
  "Drakloak": "Phandra",
  "Dragapult": "Dragapult",
  "Zacian": "Zacian",
  "Zamazenta": "Zamazenta",
  "Eternatus": "Eternatus",
  "Kubfu": "Kubfu",
  "Urshifu": "Ūraosu",
  "Rapid Strike Urshifu": "Ūraosu",
  "Zarude": "Zarude",
  "Dada Zarude": "Zarude",
  "Regieleki": "Regieleki",
  "Regidrago": "Regidrago",
  "Glastrier": "Polaross",
  "Spectrier": "Spectrier",
  "Calyrex": "Calyrex",
  "Wyrdeer": "Wyrdeer",
  "Kleavor": "Kleavor",
  "Ursaluna": "Ursaluna",
  "Bloodmoon Ursaluna": "Blutmond",
  "Basculegion": "Idaitou",
  "Sneasler": "Oonyūra",
  "Overqwil": "Harīman",
  "Enamorus": "Cupidos",
  "Sprigatito": "Felori",
  "Floragato": "Nyarote",
  "Meowscarada": "Maskagato",
  "Fuecoco": "Krokel",
  "Crocalor": "Lokroko",
  "Skeledirge": "Loudbone",
  "Quaxly": "Kwaks",
  "Quaxwell": "Welkamo",
  "Quaquaval": "Wanival",
  "Lechonk": "Lechonk",
  "Oinkologne": "Perfuton",
  "Tarountula": "Tarundel",
  "Spidops": "Spidops",
  "Nymble": "Nymble",
  "Lokix": "Lokix",
  "Pawmi": "Pamo",
  "Pawmo": "Pawmo",
  "Pawmot": "Pawmot",
  "Tandemaus": "Zwieps",
  "Maushold": "Famieps",
  "Family of Three Maushold": "Famieps",
  "Fidough": "Hefel",
  "Dachsbun": "Backel",
  "Smoliv": "Olini",
  "Dolliv": "Dolliv",
  "Arboliva": "Orīva",
  "Squawkabilly": "Ikirinko",
  "Blue Plumage Squawkabilly": "Ikirinko",
  "Yellow Plumage Squawkabilly": "Ikirinko",
  "White Plumage Squawkabilly": "Ikirinko",
  "Nacli": "Nacli",
  "Naclstack": "Jiozumu",
  "Garganacl": "Kyojiōn",
  "Charcadet": "Carbou",
  "Armarouge": "Crimanzo",
  "Ceruledge": "Ceruledge",
  "Tadbulb": "Blipp",
  "Bellibolt": "Wampitz",
  "Wattrel": "Kaiden",
  "Kilowattrel": "Voltrean",
  "Maschiff": "Mobtiff",
  "Mabosstiff": "Dogrino",
  "Shroodle": "Sproxi",
  "Grafaiai": "Affiti",
  "Bramblin": "Anokusa",
  "Brambleghast": "Horrerba",
  "Toedscool": "Tentagra",
  "Toedscruel": "Tenterra",
  "Klawf": "Klawf",
  "Capsakid": "Pimito",
  "Scovillain": "Sukoviran",
  "Rellor": "Rellor",
  "Rabsca": "Rabsca",
  "Flittle": "Flittle",
  "Espathra": "Espathra",
  "Tinkatink": "Forgita",
  "Tinkatuff": "Forgella",
  "Tinkaton": "Tinkaton",
  "Wiglett": "Wiglett",
  "Wugtrio": "Wugtrio",
  "Bombirdier": "Adebom",
  "Finizen": "Dofin",
  "Palafin": "Palafin",
  "Hero Palafin": "Palafin",
  "Varoom": "Varoom",
  "Revavroom": "Revavroom",
  "Cyclizar": "Mopex",
  "Battle Cyclizar": "Mopex",
  "Ride Cyclizar": "Mopex",
  "Orthworm": "Schlurm",
  "Glimmet": "Kirāme",
  "Glimmora": "Glimmora",
  "Greavard": "Bochi",
  "Houndstone": "Tomberro",
  "Flamigo": "Flamigo",
  "Cetoddle": "Piétacé",
  "Cetitan": "Cetitan",
  "Veluza": "Veluza",
  "Dondozo": "Dondozo",
  "Tatsugiri": "Nigiragi",
  "Droopy Tatsugiri": "Nigiragi",
  "Stretchy Tatsugiri": "Nigiragi",
  "Annihilape": "Epitaff",
  "Clodsire": "Dooh",
  "Farigiraf": "Rikikirn",
  "Dudunsparce": "Nokokotchi",
  "Three-Segment Dudunsparce": "Nokokotchi",
  "Kingambit": "Kingambit",
  "Great Tusk": "Great Tusk",
  "Scream Tail": "Scream Tail",
  "Brute Bonnet": "Wutpilz",
  "Flutter Mane": "Habtakukami",
  "Slither Wing": "Chiohauhane",
  "Sandy Shocks": "Sandfell",
  "Iron Treads": "Eisenrad",
  "Iron Bundle": "Iron Bundle",
  "Iron Hands": "Eisenhand",
  "Iron Jugulis": "Eisenhals",
  "Iron Moth": "Iron Moth",
  "Iron Thorns": "Eisendorn",
  "Frigibax": "Sebie",
  "Arctibax": "Segōru",
  "Baxcalibur": "Seglaive",
  "Gimmighoul": "Mordudor",
  "Roaming Gimmighoul": "Mordudor",
  "Gholdengo": "Surfugo",
  "Wo-Chien": "Wo-Chien",
  "Chien-Pao": "Paojian",
  "Ting-Lu": "Dinlu",
  "Chi-Yu": "Īyui",
  "Roaring Moon": "Rugit-Lune",
  "Iron Valiant": "Iron Valiant",
  "Koraidon": "Koraidon",
  "Sprinting Build Koraidon": "Koraidon",
  "Gliding Build Koraidon": "Koraidon",
  "Miraidon": "Miraidon",
  "Drive Mode Miraidon": "Miraidon",
  "Glide Mode Miraidon": "Miraidon",
  "Walking Wake": "Windewoge",
  "Iron Leaves": "Eisenblatt",
  "Dipplin": "Dipplin",
  "Poltchageist": "Poltchageist",
  "Sinistcha": "Sinistcha",
  "Okidogi": "Okidogi",
  "Munkidori": "Munkidori",
  "Fezandipiti": "Fezandipiti",
  "Ogerpon": "Ogerpon",
  "Wellspring Mask Ogerpon": "Ogerpon",
  "Hearthflame Mask Ogerpon": "Ogerpon",
  "Cornerstone Mask Ogerpon": "Ogerpon",
  "Archaludon": "Briduras",
  "Hydrapple": "Hydrapple",
  "Gouging Fire": "Keilflamme",
  "Raging Bolt": "Ire-Foudre",
  "Iron Boulder": "Eisenfels",
  "Iron Crown": "Iron Crown",
  "Terapagos": "Terapagos",
  "Terastal Terapagos": "Terapagos",
  "Pecharunt": "Infamomo"
}
